{
  "data":[
    {
      "id":"1",
      "avatar":"https://baike.baidu.com/pic/%E9%BA%A6%E5%BD%93%E5%8A%B3/163033/0/f603918fa0ec08fa1f4cf9615aee3d6d54fbdaac?fr=lemma&ct=single",
      "name":"金拱门",
      "favorableRate":"88%",
      "discover":"880"
    },{
      "id":"1",
      "avatar":"https://baike.baidu.com/pic/%E9%BA%A6%E5%BD%93%E5%8A%B3/163033/0/f603918fa0ec08fa1f4cf9615aee3d6d54fbdaac?fr=lemma&ct=single",
      "name":"金拱门",
      "favorableRate":"88%",
      "discover":"880"
    },{
      "id":"1",
      "avatar":"https://baike.baidu.com/pic/%E9%BA%A6%E5%BD%93%E5%8A%B3/163033/0/f603918fa0ec08fa1f4cf9615aee3d6d54fbdaac?fr=lemma&ct=single",
      "name":"金拱门",
      "favorableRate":"88%",
      "discover":"880"
    },{
      "id":"1",
      "avatar":"https://baike.baidu.com/pic/%E9%BA%A6%E5%BD%93%E5%8A%B3/163033/0/f603918fa0ec08fa1f4cf9615aee3d6d54fbdaac?fr=lemma&ct=single",
      "name":"金拱门",
      "favorableRate":"88%",
      "discover":"880"
    },{
      "id":"1",
      "avatar":"https://baike.baidu.com/pic/%E9%BA%A6%E5%BD%93%E5%8A%B3/163033/0/f603918fa0ec08fa1f4cf9615aee3d6d54fbdaac?fr=lemma&ct=single",
      "name":"金拱门",
      "favorableRate":"88%",
      "discover":"880"
    },{
      "id":"1",
      "avatar":"https://baike.baidu.com/pic/%E9%BA%A6%E5%BD%93%E5%8A%B3/163033/0/f603918fa0ec08fa1f4cf9615aee3d6d54fbdaac?fr=lemma&ct=single",
      "name":"金拱门",
      "favorableRate":"88%",
      "discover":"880"
    }
    
  ]
}
